XTestRunner/__init__.py
XTestRunner/_dingtalk.py
XTestRunner/_email.py
XTestRunner/_feishu.py
XTestRunner/_weixin.py
XTestRunner/config.py
XTestRunner/html/__init__.py
XTestRunner/html/heading-en.html
XTestRunner/html/heading-zh-CN.html
XTestRunner/html/img_tmpl.html
XTestRunner/html/mail-en.html
XTestRunner/html/mail-zh-CN.html
XTestRunner/html/notice_tmp.md
XTestRunner/html/report-en.html
XTestRunner/html/report-zh-CN.html
XTestRunner/html/report_class.html
XTestRunner/html/report_test_no_output.html
XTestRunner/html/report_test_with_output.html
XTestRunner/html/static/css/seldom-main.css
XTestRunner/html/static/css/seldom-utilities.css
XTestRunner/html/static/images/XReport_logo.png
XTestRunner/html/static/images/XTestRunner_logo.jpg
XTestRunner/html/static/images/XTestRunnerIcon.png
XTestRunner/html/static/js/echarts.min.js
XTestRunner/html/static/js/jquery.min.js
XTestRunner/html/stylesheet.html
XTestRunner/html/template.html
XTestRunner/htmlrunner/__init__.py
XTestRunner/htmlrunner/multi_language.py
XTestRunner/htmlrunner/result.py
XTestRunner/htmlrunner/runner.py
XTestRunner/version.py
XTestRunner/xmlrunner/__init__.py
XTestRunner/xmlrunner/result.py
XTestRunner/xmlrunner/runner.py
xtestrunner-1.8.6.dist-info/licenses/LICENSE
xtestrunner-1.8.6.dist-info/METADATA
xtestrunner-1.8.6.dist-info/WHEEL
xtestrunner-1.8.6.dist-info/RECORD
