Metadata-Version: 2.4
Name: XTestRunner
Version: 1.8.6
Summary: Modern style test report based on unittest framework.
License: Apache-2.0
License-File: LICENSE
Author: bugmaster
Author-email: fnngj@126.com
Requires-Python: >=3.8,<4.0
Classifier: Intended Audience :: Developers
Classifier: License :: OSI Approved :: Apache Software License
Classifier: Operating System :: MacOS :: MacOS X
Classifier: Operating System :: Microsoft :: Windows
Classifier: Programming Language :: Python
Classifier: Programming Language :: Python :: 3
Classifier: Programming Language :: Python :: 3.8
Classifier: Programming Language :: Python :: 3.9
Classifier: Programming Language :: Python :: 3.10
Classifier: Programming Language :: Python :: 3.11
Classifier: Programming Language :: Python :: 3.12
Classifier: Programming Language :: Python :: 3.13
Classifier: Programming Language :: Python :: 3.14
Classifier: Topic :: Internet :: WWW/HTTP :: Dynamic Content
Classifier: Topic :: Software Development :: Testing
Classifier: Topic :: Software Development :: Version Control :: Git
Requires-Dist: jinja2 (>=3.1.6,<4.0.0)
Requires-Dist: requests (>=2.31.0)
Project-URL: Homepage, https://github.com/seldomQA/XTestRunner/
Project-URL: Repository, https://github.com/seldomQA/XTestRunner/
